mlp_mixer/__init__.py
mlp_mixer/mixer.py
mlp_mixer-0.0.1.dist-info/LICENSE
mlp_mixer-0.0.1.dist-info/METADATA
mlp_mixer-0.0.1.dist-info/WHEEL
mlp_mixer-0.0.1.dist-info/top_level.txt
mlp_mixer-0.0.1.dist-info/RECORD
