Metadata-Version: 2.1
Name: mlp-mixer
Version: 0.0.1
Summary: Pytorch implementation of MLPMixer
Home-page: https://github.com/himanshu-dutta/MLPMixer-pytorch
Author: Himanshu Dutta
Author-email: meet.himanshu.dutta@gmail.com
License: MIT
Keywords: deep learning,image classification
Platform: UNKNOWN
Classifier: Development Status :: 4 - Beta
Classifier: Intended Audience :: Developers
Classifier: License :: OSI Approved :: MIT License
Classifier: Programming Language :: Python :: 3.6
Classifier: Programming Language :: Python :: 3.7
Classifier: Programming Language :: Python :: 3.8
Classifier: Programming Language :: Python :: 3.9
Requires-Python: >3.6
Requires-Dist: torch (>=1.6)
